[
  {
    "id": 306,
    "day": 62,
    "word": "bleed",
    "traduction": "** preencher **",
    "level": null,
    "class": "verb",
    "observation": null,
    "example": null,
    "sound": null
  },
  {
    "id": 307,
    "day": 62,
    "word": "deny",
    "traduction": "** preencher **",
    "level": null,
    "class": "verb",
    "observation": null,
    "example": null,
    "sound": null
  },
  {
    "id": 308,
    "day": 62,
    "word": "Guess",
    "traduction": "** preencher **",
    "level": null,
    "class": "verb",
    "observation": null,
    "example": null,
    "sound": null
  },
  {
    "id": 309,
    "day": 62,
    "word": "narrow",
    "traduction": "** preencher **",
    "level": null,
    "class": "verb",
    "observation": null,
    "example": null,
    "sound": null
  },
  {
    "id": 310,
    "day": 62,
    "word": "request",
    "traduction": "** preencher **",
    "level": null,
    "class": "verb",
    "observation": null,
    "example": null,
    "sound": null
  }
]