[
  {
    "id": 196,
    "day": 40,
    "word": "Rain",
    "traduction": "chover|chuva",
    "level": "A1",
    "class": "verb|noun",
    "observation": null,
    "example": null,
    "sound": null
  },
  {
    "id": 197,
    "day": 40,
    "word": "record",
    "traduction": "gravar",
    "level": "A2",
    "class": "verb",
    "observation": null,
    "example": null,
    "sound": null
  },
  {
    "id": 198,
    "day": 40,
    "word": "remain",
    "traduction": "permanecer|ficar",
    "level": "B1",
    "class": "verb",
    "observation": null,
    "example": null,
    "sound": null
  },
  {
    "id": 199,
    "day": 40,
    "word": "rescue",
    "traduction": "resgatar|salvar",
    "level": "B1",
    "class": "verb",
    "observation": null,
    "example": null,
    "sound": null
  },
  {
    "id": 200,
    "day": 40,
    "word": "respect",
    "traduction": "respeitar|respeito",
    "level": "B1",
    "class": "verb|noun",
    "observation": null,
    "example": null,
    "sound": null
  }
]