[
  {
    "id": 505,
    "day": 74,
    "word": "turn",
    "traduction": "girar",
    "level": "B2",
    "class": "verb",
    "observation": null,
    "example": null,
    "sound": null
  },
  {
    "id": 506,
    "day": 74,
    "word": "adapt",
    "traduction": "adaptar|ajustar",
    "level": "B2",
    "class": "verb",
    "observation": null,
    "example": null,
    "sound": null
  },
  {
    "id": 507,
    "day": 74,
    "word": "affect",
    "traduction": "afetar|influir em",
    "level": "B2",
    "class": "verb",
    "observation": null,
    "example": null,
    "sound": null
  },
  {
    "id": 508,
    "day": 74,
    "word": "approve",
    "traduction": "aprovar|aceitar",
    "level": "B2",
    "class": "verb",
    "observation": null,
    "example": null,
    "sound": null
  },
  {
    "id": 509,
    "day": 74,
    "word": "practice",
    "traduction": "praticar",
    "level": "B2",
    "class": "verb",
    "observation": null,
    "example": null,
    "sound": null
  },
  {
    "id": 510,
    "day": 74,
    "word": "practice",
    "traduction": "prática",
    "level": "B2",
    "class": "noun",
    "observation": null,
    "example": null,
    "sound": null
  }
]