[
  {
    "id": 281,
    "day": 57,
    "word": "avoid",
    "traduction": "evitar",
    "level": "B1",
    "class": "verb",
    "observation": null,
    "example": null,
    "sound": null
  },
  {
    "id": 282,
    "day": 57,
    "word": "cycle",
    "traduction": "bicicleta|ciclo",
    "level": "B2",
    "class": "noun",
    "observation": null,
    "example": null,
    "sound": null
  },
  {
    "id": 283,
    "day": 57,
    "word": "frighten",
    "traduction": "assustar",
    "level": "B2",
    "class": "verb",
    "observation": null,
    "example": null,
    "sound": null
  },
  {
    "id": 284,
    "day": 57,
    "word": "Meet",
    "traduction": "encontrar|conhecer",
    "level": "A1",
    "class": "verb",
    "observation": null,
    "example": null,
    "sound": null
  },
  {
    "id": 285,
    "day": 57,
    "word": "Relax",
    "traduction": "relaxar",
    "level": "B1",
    "class": "verb",
    "observation": null,
    "example": null,
    "sound": null
  }
]