[
  {
    "id": 21,
    "day": 5,
    "word": "arrive",
    "traduction": "chegar",
    "level": "A2",
    "class": "verb",
    "observation": null,
    "example": null,
    "sound": null
  },
  {
    "id": 22,
    "day": 5,
    "word": "begin",
    "traduction": "começar|iniciar",
    "level": "A1",
    "class": "verb",
    "observation": null,
    "example": "What time does the concert begin?",
    "sound": null
  },
  {
    "id": 23,
    "day": 5,
    "word": "cook",
    "traduction": "cozinhar",
    "level": "A1",
    "class": "verb",
    "observation": null,
    "example": "I don't cook meat very often.",
    "sound": null
  },
  {
    "id": 25,
    "day": 5,
    "word": "departure",
    "traduction": "partida|saída",
    "level": "B1",
    "class": "noun",
    "observation": null,
    "example": null,
    "sound": null
  },
  {
    "id": 24,
    "day": 5,
    "word": "finish",
    "traduction": "terminar|acabar|concluir",
    "level": "A1",
    "class": "verb",
    "observation": null,
    "example": null,
    "sound": null
  }
]