[
  {
    "id": 356,
    "day": 72,
    "word": "charge",
    "traduction": "** preencher **",
    "level": null,
    "class": "verb",
    "observation": null,
    "example": null,
    "sound": null
  },
  {
    "id": 357,
    "day": 72,
    "word": "dump",
    "traduction": "** preencher **",
    "level": null,
    "class": "verb",
    "observation": null,
    "example": null,
    "sound": null
  },
  {
    "id": 358,
    "day": 72,
    "word": "Hurt",
    "traduction": "** preencher **",
    "level": null,
    "class": "verb",
    "observation": null,
    "example": null,
    "sound": null
  },
  {
    "id": 359,
    "day": 72,
    "word": "Perform",
    "traduction": "** preencher **",
    "level": null,
    "class": "verb",
    "observation": null,
    "example": null,
    "sound": null
  },
  {
    "id": 360,
    "day": 72,
    "word": "Scare",
    "traduction": "** preencher **",
    "level": null,
    "class": "verb",
    "observation": null,
    "example": null,
    "sound": null
  }
]