[
  {
    "id": 690,
    "day": 54,
    "word": "bleed",
    "traduction": "sangrar",
    "class": "verb",
    "examples": "He is bleeding.",
    "synonyms": "hemorrhage|lose blood",
    "sound": null
  },
  {
    "id": 691,
    "day": 54,
    "word": "down",
    "traduction": "baixo",
    "class": "adverb",
    "examples": "Sit down.",
    "synonyms": "below|downward",
    "sound": null
  },
  {
    "id": 692,
    "day": 54,
    "word": "up",
    "traduction": "cima",
    "class": "adverb",
    "examples": "Look up.",
    "synonyms": "above|upward",
    "sound": null
  },
  {
    "id": 693,
    "day": 54,
    "word": "Italian",
    "traduction": "italiano",
    "class": "substantive",
    "examples": "Italian is spoken in Italy.",
    "synonyms": "language|tongue",
    "sound": null
  },
  {
    "id": 694,
    "day": 54,
    "word": "alligator",
    "traduction": "jacaré",
    "class": "substantive",
    "examples": "The alligator is big.",
    "synonyms": "reptile|crocodile",
    "sound": null
  },
  {
    "id": 695,
    "day": 54,
    "word": "crocodile",
    "traduction": "crocodilo",
    "class": "substantive",
    "examples": "The crocodile is dangerous.",
    "synonyms": "reptile|alligator",
    "sound": null
  },
  {
    "id": 696,
    "day": 54,
    "word": "crop",
    "traduction": "plantação",
    "class": "substantive",
    "examples": "The crop is ready.",
    "synonyms": "harvest|yield",
    "sound": null
  },
  {
    "id": 697,
    "day": 54,
    "word": "moth",
    "traduction": "mariposa",
    "class": "substantive",
    "examples": "The moth flies at night.",
    "synonyms": "insect|butterfly",
    "sound": null
  },
  {
    "id": 698,
    "day": 54,
    "word": "root",
    "traduction": "raiz",
    "class": "substantive",
    "examples": "The root is deep.",
    "synonyms": "base|origin",
    "sound": null
  },
  {
    "id": 699,
    "day": 54,
    "word": "stem",
    "traduction": "caule",
    "class": "substantive",
    "examples": "The stem is long.",
    "synonyms": "stalk|shoot",
    "sound": null
  },
  {
    "id": 700,
    "day": 54,
    "word": "wasp",
    "traduction": "vespa",
    "class": "substantive",
    "examples": "The wasp stings.",
    "synonyms": "insect|hornet",
    "sound": null
  },
  {
    "id": 701,
    "day": 54,
    "word": "web",
    "traduction": "teia",
    "class": "substantive",
    "examples": "The spider makes a web.",
    "synonyms": "net|mesh",
    "sound": null
  },
  {
    "id": 702,
    "day": 54,
    "word": "noon",
    "traduction": "meio-dia",
    "class": "substantive",
    "examples": null,
    "synonyms": null,
    "sound": null
  }
]